insteonlocal
