Metadata-Version: 1.1
Name: insteonlocal
Version: 0.51
Summary: InsteonLocal allows local (non-cloud) control of the Insteon Hub 2245-222
Home-page: https://github.com/phareous/insteonlocal
Author: Michael Long
Author-email: mplong@gmail.com
License: UNKNOWN
Download-URL: https://github.com/phareous/insteonlocal/tarball/0.51
Keywords: insteon
Platform: UNKNOWN
Requires: requests
Requires: time
Requires: pprint
Requires: logging
Requires: logging.handlers
Requires: sys
Requires: json
Requires: collections
Provides: insteonlocal
